README.rst
setup.py
pyardrone/__init__.py
pyardrone/config.py
pyardrone.egg-info/PKG-INFO
pyardrone.egg-info/SOURCES.txt
pyardrone.egg-info/dependency_links.txt
pyardrone.egg-info/top_level.txt
pyardrone/at/__init__.py
pyardrone/at/base.py
pyardrone/at/parameters.py
pyardrone/navdata/__init__.py
pyardrone/navdata/options.py
pyardrone/navdata/states.py
pyardrone/utils/__init__.py
pyardrone/utils/dochelper.py
pyardrone/utils/logging.py
pyardrone/utils/structure.py