Metadata-Version: 1.1
Name: pyardrone
Version: 0.3.3.dev1
Summary: Controlling Parrot AR.Drone with Python
Home-page: http://github.com/afg984/pyardrone
Author: afg984
Author-email: afg984@gmail.com
License: MIT License
Platform: UNKNOWN
Classifier: Development Status :: 2 - Pre-Alpha
Classifier: Intended Audience :: Developers
Classifier: License :: OSI Approved :: MIT License
Classifier: Operating System :: OS Independent
Classifier: Programming Language :: Python
Classifier: Programming Language :: Python :: 3
Classifier: Programming Language :: Python :: 3.4
